predict_test/__init__.py
predict_test_01/__init__.py
predict_test_01/untitled0.py
predict_test_02/__init__.py
predict_test_03/__init__.py
predict_test_03/untitled0.py
predict_test_04/__init__.py
predict_test_05/__init__.py
prediict/__init__.py
src/__init__.py
src/data/__init__.py
src/data/make_dataset.py
src/features/__init__.py
src/features/build_features.py
src/models/__init__.py
src/models/adaboost.py
src/models/grad_boost.py
src/models/knn.py
src/models/logistic.py
src/models/mlp.py
src/models/perceptron.py
src/models/random_forest.py
src/models/sgd.py
src/models/support_vector.py
src/models/visualize.py
src/models/xgboost.py
src/visualization/__init__.py
src/visualization/visualize.py
predict_test_v6-0.1.0.dist-info/LICENSE
predict_test_v6-0.1.0.dist-info/METADATA
predict_test_v6-0.1.0.dist-info/WHEEL
predict_test_v6-0.1.0.dist-info/top_level.txt
predict_test_v6-0.1.0.dist-info/RECORD
